Workbook

Sheet Inputs
A1: COMPANY VALUATION MODEL v2.2 — INPUTS
A2: Every input is either taken directly from the financial statements or is an industry-, country- or market-wide parameter. No company-specific judgement values are used anywhere in this workbook.
A4: 1. COMPANY IDENTIFICATION
A6: Company name | B6: FICTIONAL DEMO SA
A7: Ticker | B7: DEMO.MI
A8: Reporting currency | B8: EUR
A9: Financial units | B9: Millions
A10: Latest fiscal year (FY0) | B10: 2025
A11: Valuation date | B11: 2026-08-19
A13: 2. MARKET DATA (as of the valuation date)
A14: Current share price | B14: 24.5 | G14: Primary listing, same currency as the statements.
A15: Diluted shares outstanding (millions) | B15: 420 | G15: Point-in-time from the latest balance sheet, not weighted average.
A16: Market capitalisation (millions) | B16: =B14*B15 -> 10290 | G16: Calculated.
A18: 3. INCOME STATEMENT — five fiscal years (millions)
B19: FY-4 | C19: FY-3 | D19: FY-2 | E19: FY-1 | F19: FY0
A20: Revenue | B20: 3800 | C20: 3950 | D20: 4180 | E20: 4310 | F20: 4520
A21: EBIT | B21: 420 | C21: 455 | D21: 500 | E21: 505 | F21: 545
A22: Depreciation & amortisation | B22: 290 | C22: 300 | D22: 315 | E22: 322 | F22: 335
A23: Interest expense (gross) | B23: 62 | C23: 60 | D23: 58 | E23: 61 | F23: 59
A24: Pre-tax income | B24: 358 | C24: 398 | D24: 445 | E24: 447 | F24: 490
A25: Income tax expense | B25: 97 | C25: 107 | D25: 120 | E25: 121 | F25: 132
A26: Net income attributable to common shareholders | B26: 255 | C26: 285 | D26: 320 | E26: 320 | F26: 352
A28: 4. BALANCE SHEET (millions)
B29: FY-4 | C29: FY-3 | D29: FY-2 | E29: FY-1 | F29: FY0
A30: Cash & cash equivalents | B30: 210 | C30: 235 | D30: 260 | E30: 275 | F30: 300
A31: Short-term investments / marketable securities | B31: 40 | C31: 45 | D31: 50 | E31: 55 | F31: 60
A32: Total current assets | B32: 1450 | C32: 1520 | D32: 1610 | E32: 1665 | F32: 1750
A33: Total current liabilities | B33: 1180 | C33: 1225 | D33: 1290 | E33: 1330 | F33: 1390
A34: Short-term debt + current portion of LTD (incl. current leases) | B34: 150 | C34: 145 | D34: 160 | E34: 155 | F34: 165
A35: Long-term debt incl. capitalised lease liabilities | B35: 1250 | C35: 1220 | D35: 1240 | E35: 1210 | F35: 1180
A36: Preferred stock | B36: 0 | C36: 0 | D36: 0 | E36: 0 | F36: 0
A37: Minority / non-controlling interest | B37: 45 | C37: 48 | D37: 52 | E37: 55 | F37: 58
A38: Total equity (incl. minority interest and preferred) | B38: 1620 | C38: 1720 | D38: 1850 | E38: 1960 | F38: 2100
A39: Equity-method investments / investments in associates | B39: 85 | C39: 88 | D39: 92 | E39: 95 | F39: 100
A40: Total assets | B40: 4400 | C40: 4560 | D40: 4790 | E40: 4930 | F40: 5150 | G40: Used by the holding-company diagnostic only; not part of the valuation chain.
A42: 5. CASH-FLOW STATEMENT (millions)
B43: FY-4 | C43: FY-3 | D43: FY-2 | E43: FY-1 | F43: FY0
A44: Capital expenditure (positive) | B44: 355 | C44: 370 | D44: 395 | E44: 405 | F44: 420
A45: Acquisitions, net of divestitures | B45: 0 | C45: 40 | D45: 0 | E45: 25 | F45: 0
A47: 6. MARKET-WIDE PARAMETERS — update quarterly, identical for every company
A48: Risk-free rate — 10y EUR AAA sovereign | B48: 0.026 | G48: ECB Data Portal, euro-area AAA curve. One rate for the whole EUR universe.
A49: Mature-market equity risk premium | B49: 0.048
A50: Long-run nominal growth — euro area (terminal ceiling) | B50: 0.032
A52: 7. COUNTRY PARAMETERS — by country of domicile
A53: Country risk premium | B53: 0.015 | G53: Damodaran country risk premiums. Zero for core, non-zero for periphery.
A54: Statutory / marginal corporate tax rate | B54: 0.24
A56: 8. INDUSTRY PARAMETERS — by industry, identical for every company in that industry
A57: Unlevered (asset) beta | B57: 0.85 | G57: Damodaran European industry data, refreshed annually. Use the PLAIN unlevered beta, not the cash-corrected column: Valuation!D35 relevers at gross debt, so the cash-corrected figure would understate the cost of equity for every company.
A58: Sales-to-capital ratio | B58: 1.6
A59: Median EBIT margin | B59: 0.105 | G59: Medians computed from your own universe snapshot. Diagnostics only — they do not enter the valuation.
A60: Median ROIC | B60: 0.095
A62: 9. MODEL CONVENTIONS — do not change between companies
A63: Stage 1 length (years) | B63: 5
A64: Stage 2 fade length (years) | B64: 5
A65: Maximum fundamental growth rate | B65: 0.12
A66: Maximum normalised ROIC | B66: 0.4
A67: Minimum normalised ROIC | B67: 0.02
A68: Maximum reinvestment rate | B68: 0.9
A69: Mid-year discounting (1 = on) | B69: 1
A70: Minimum WACC minus terminal growth spread | B70: 0.005

Sheet RefData
A1: SYNTHETIC CREDIT RATING — INTEREST COVERAGE TO DEFAULT SPREAD
A2: Interest coverage = normalised EBIT / median gross interest expense. The model looks up the highest threshold the company clears and adds that spread to the risk-free rate.
A3: Coverage ratio >= | B3: Implied rating | C3: Default spread
A4: -100000 | B4: D | C4: 0.19 | D4: Source: Damodaran, 'Ratings, Interest Coverage Ratios and Default Spreads' (large non-financial firms). Refresh annually. These are the only hardcoded market data in the workbook.
A5: 0.2 | B5: C | C5: 0.16
A6: 0.65 | B6: CC | C6: 0.1261
A7: 0.8 | B7: CCC | C7: 0.0885
A8: 1.25 | B8: B- | C8: 0.0509
A9: 1.5 | B9: B | C9: 0.0321
A10: 1.75 | B10: B+ | C10: 0.0275
A11: 2 | B11: BB | C11: 0.0184
A12: 2.25 | B12: BB+ | C12: 0.0138
A13: 2.5 | B13: BBB | C13: 0.0111
A14: 3 | B14: A- | C14: 0.0089
A15: 4.25 | B15: A | C15: 0.0078
A16: 5.5 | B16: A+ | C16: 0.007
... A18: 8.5 | B18: AAA | C18: 0.004
A20: Thresholds must remain sorted ascending — MATCH(...,1) depends on it.
A22: Active table (LARGE or SMALL) | B22: LARGE
A23: Table vintage (YYYY-MM of publication) | B23: 2026-01
A24: Size cut-off — market cap, EUR millions | B24: 4300
A26: A4:C18 holds whichever table applies to this company. The pipeline writes all 45 cells from refdata_tables.json before recalculating, then D120 verifies the choice against market capitalisation. Cut-off is Damodaran's USD 5bn converted at 1.16 and FIXED in EUR: review it each February with the tables, never float it with the exchange rate.

Sheet Valuation
B1: VALUATION ENGINE v2.2
B3: A. NORMALISED OPERATING PERFORMANCE (five-year median)
D4: FY-4 | E4: FY-3 | F4: FY-2 | G4: FY-1 | H4: FY0
B5: Revenue, FY0 | D5: =Inputs!F20 -> 4520
B6: EBIT margin by year | D6: =IFERROR(Inputs!B21/Inputs!B20,0) -> 0.11052632 | E6: =IFERROR(Inputs!C21/Inputs!C20,0) -> 0.11518987 | F6: =IFERROR(Inputs!D21/Inputs!D20,0) -> 0.11961722 | G6: =IFERROR(Inputs!E21/Inputs!E20,0) -> 0.11716937 | H6: =IFERROR(Inputs!F21/Inputs!F20,0) -> 0.12057522
B7: Normalised EBIT margin (median of 5) | D7: =MEDIAN(D6:H6) -> 0.11716937 | N7: Median, not mean: one distorted year cannot move it.
B8: Normalised EBIT | D8: =D5*D7 -> 529.60557
B9: Effective tax rate by year | D9: =IFERROR(Inputs!B25/Inputs!B24,0) -> 0.27094972 | E9: =IFERROR(Inputs!C25/Inputs!C24,0) -> 0.26884422 | F9: =IFERROR(Inputs!D25/Inputs!D24,0) -> 0.26966292 | G9: =IFERROR(Inputs!E25/Inputs!E24,0) -> 0.27069351 | H9: =IFERROR(Inputs!F25/Inputs!F24,0) -> 0.26938776
B10: Median effective tax rate | D10: =MEDIAN(D9:H9) -> 0.26966292
B11: Normalised tax rate (stage-1 starting point) | D11: =IF(OR(D10<0.05,D10>0.45),Inputs!B54,D10) -> 0.26966292 | N11: Falls back to the statutory rate only when the median is implausible.
B12: Normalised NOPAT | D12: =D8*(1-D11) -> 386.79058
B14: B. INVESTED CAPITAL AND RETURNS
D15: FY-4 | E15: FY-3 | F15: FY-2 | G15: FY-1 | H15: FY0
B16: Invested capital | D16: =Inputs!B34+Inputs!B35+Inputs!B38-Inputs!B30-Inputs!B31-Inputs!B39 -> 2685 | E16: =Inputs!C34+Inputs!C35+Inputs!C38-Inputs!C30-Inputs!C31-Inputs!C39 -> 2717 | F16: =Inputs!D34+Inputs!D35+Inputs!D38-Inputs!D30-Inputs!D31-Inputs!D39 -> 2848 | G16: =Inputs!E34+Inputs!E35+Inputs!E38-Inputs!E30-Inputs!E31-Inputs!E39 -> 2900 | H16: =Inputs!F34+Inputs!F35+Inputs!F38-Inputs!F30-Inputs!F31-Inputs!F39 -> 2985
B17: Working capital (ex cash, ex short-term debt) | D17: =(Inputs!B32-Inputs!B30-Inputs!B31)-(Inputs!B33-Inputs!B34) -> 170 | E17: =(Inputs!C32-Inputs!C30-Inputs!C31)-(Inputs!C33-Inputs!C34) -> 160 | F17: =(Inputs!D32-Inputs!D30-Inputs!D31)-(Inputs!D33-Inputs!D34) -> 170 | G17: =(Inputs!E32-Inputs!E30-Inputs!E31)-(Inputs!E33-Inputs!E34) -> 160 | H17: =(Inputs!F32-Inputs!F30-Inputs!F31)-(Inputs!F33-Inputs!F34) -> 165
B18: Average invested capital (FY-1, FY0) | D18: =AVERAGE(G16:H16) -> 2942.5
B19: Raw normalised ROIC | D19: =IF(D18<=0,Inputs!B66,D12/D18) -> 0.13144965
B20: Bounded normalised ROIC | D20: =MIN(Inputs!B66,MAX(Inputs!B67,D19)) -> 0.13144965
B22: C. REINVESTMENT (two independent estimates, conservative one selected)
B23: Cumulative net reinvestment, FY-3 to FY0 | D23: =SUM(Inputs!C44:F44)+SUM(Inputs!C45:F45)-SUM(Inputs!C22:F22)+(H17-D17) -> 378 | N23: Capex + acquisitions - D&A + change in working capital, over four years.
B24: Cumulative NOPAT, FY-3 to FY0 | D24: =SUM(Inputs!C21:F21)*(1-D11) -> 1464.3258
B25: Reinvestment rate — cash-flow based | D25: =IF(D24<=0,0,D23/D24) -> 0.25813927
B26: Revenue CAGR, FY-4 to FY0 | D26: =IFERROR(IF(Inputs!B20<=0,0,(Inputs!F20/Inputs!B20)^(1/4)-1),0) -> 0.044332298
B27: Implied reinvestment — sales-to-capital based | D27: =IFERROR(D5*MAX(0,D26)/Inputs!B58,0) -> 125.23874 | N27: Revenue growth divided by the industry sales-to-capital ratio.
B28: Reinvestment rate — sales-to-capital based | D28: =IF(D12<=0,0,D27/D12) -> 0.32378953
B29: Selected reinvestment rate (lower of the two) | D29: =MIN(Inputs!B68,MAX(0,MIN(D25,D28))) -> 0.25813927 | N29: The lower estimate produces the lower growth rate. Conservative by rule, not by judgement.
B30: Divergence between the two estimates | D30: =IFERROR(ABS(D25-D28)/MAX(ABS(D25),ABS(D28)),0) -> 0.20275598
B32: D. COST OF CAPITAL
B33: Total debt, FY0 | D33: =Inputs!F34+Inputs!F35 -> 1345
B34: Debt / equity (market) | D34: =IFERROR(D33/Inputs!B16,0) -> 0.13070943
B35: Relevered equity beta | D35: =Inputs!B57*(1+(1-Inputs!B54)*D34) -> 0.93443829 | N35: Bottom-up: industry asset beta relevered at this company's own capital structure. No regression.
B36: Cost of equity | D36: =Inputs!B48+D35*Inputs!B49+Inputs!B53 -> 0.085853038
B37: Median gross interest expense | D37: =MEDIAN(Inputs!B23:F23) -> 60
B38: Interest coverage ratio | D38: =IF(D37<=0,100,D8/D37) -> 8.8267595
B39: Implied credit rating | D39: =INDEX(RefData!B4:B18,MATCH(D38,RefData!A4:A18,1)) -> AAA
B40: Synthetic default spread | D40: =INDEX(RefData!C4:C18,MATCH(D38,RefData!A4:A18,1)) -> 0.004
B41: Synthetic pre-tax cost of debt | D41: =Inputs!B48+D40+Inputs!B53 -> 0.045
B42: Actual effective interest rate | D42: =IFERROR(IF(AVERAGE(Inputs!E34:E35,Inputs!F34:F35)<=0,0,Inputs!F23/((Inputs!E34+Inputs!E35+Inputs!F34+Inputs!F35)/2)),0) -> 0.043542435 | N42: Gross interest expense over average gross debt. Straight from the statements.
B43: Pre-tax cost of debt (higher of the two, capped) | D43: =MIN(0.25,MAX(D41,D42)) -> 0.045 | N43: Taking the higher is conservative and mechanical; the cap stops a data error from dominating.
B44: After-tax cost of debt | D44: =D43*(1-Inputs!B54) -> 0.0342
B45: Equity weight | D45: =IF(Inputs!B16+D33<=0,1,Inputs!B16/(Inputs!B16+D33)) -> 0.88440052
B46: Debt weight | D46: =1-D45 -> 0.11559948
B47: WACC | D47: =D45*D36+D46*D44 -> 0.079881973
B49: E. GROWTH, FADE AND TERMINAL ASSUMPTIONS
B50: Fundamental growth rate (stage 1) | D50: =MIN(Inputs!B65,MAX(0,D29*D20)) -> 0.033932315 | N50: Reinvestment rate x ROIC. Never an assumed number.
B51: Terminal growth rate | D51: =MIN(Inputs!B48,Inputs!B50) -> 0.026
B52: Terminal ROIC | D52: =MAX(D47,D51+Inputs!B70) -> 0.079881973 | N52: Converges to WACC: no perpetual excess returns.
B53: Terminal tax rate | D53: =Inputs!B54 -> 0.24
B54: Mid-year discounting offset | D54: =IF(Inputs!B69=1,0.5,0) -> 0.5
B55: Forecast horizon (years) | D55: =Inputs!B63+Inputs!B64 -> 10
B57: F. EXPLICIT FORECAST (years 1 to 10)
B58: Year | D58: 1 | E58: 2 | F58: 3 | G58: 4 | H58: 5 | I58: 6 | J58: 7 | K58: 8 | L58: 9 | M58: 10
B59: Growth rate | D59: =IF(1<=Inputs!$B$63,$D$50,$D$50+($D$51-$D$50)*(1-Inputs!$B$63)/Inputs!$B$64) -> 0.033932315 | E59: =IF(2<=Inputs!$B$63,$D$50,$D$50+($D$51-$D$50)*(2-Inputs!$B$63)/Inputs!$B$64) -> 0.033932315 | F59: =IF(3<=Inputs!$B$63,$D$50,$D$50+($D$51-$D$50)*(3-Inputs!$B$63)/Inputs!$B$64) -> 0.033932315 | G59: =IF(4<=Inputs!$B$63,$D$50,$D$50+($D$51-$D$50)*(4-Inputs!$B$63)/Inputs!$B$64) -> 0.033932315 | H59: =IF(5<=Inputs!$B$63,$D$50,$D$50+($D$51-$D$50)*(5-Inputs!$B$63)/Inputs!$B$64) -> 0.033932315 | I59: =IF(6<=Inputs!$B$63,$D$50,$D$50+($D$51-$D$50)*(6-Inputs!$B$63)/Inputs!$B$64) -> 0.032345852 | J59: =IF(7<=Inputs!$B$63,$D$50,$D$50+($D$51-$D$50)*(7-Inputs!$B$63)/Inputs!$B$64) -> 0.030759389 | K59: =IF(8<=Inputs!$B$63,$D$50,$D$50+($D$51-$D$50)*(8-Inputs!$B$63)/Inputs!$B$64) -> 0.029172926 | L59: =IF(9<=Inputs!$B$63,$D$50,$D$50+($D$51-$D$50)*(9-Inputs!$B$63)/Inputs!$B$64) -> 0.027586463 | M59: =IF(10<=Inputs!$B$63,$D$50,$D$50+($D$51-$D$50)*(10-Inputs!$B$63)/Inputs!$B$64) -> 0.026
B60: ROIC (fading to terminal ROIC) | D60: =IF(1<=Inputs!$B$63,$D$20,$D$20+($D$52-$D$20)*(1-Inputs!$B$63)/Inputs!$B$64) -> 0.13144965 | E60: =IF(2<=Inputs!$B$63,$D$20,$D$20+($D$52-$D$20)*(2-Inputs!$B$63)/Inputs!$B$64) -> 0.13144965 | F60: =IF(3<=Inputs!$B$63,$D$20,$D$20+($D$52-$D$20)*(3-Inputs!$B$63)/Inputs!$B$64) -> 0.13144965 | G60: =IF(4<=Inputs!$B$63,$D$20,$D$20+($D$52-$D$20)*(4-Inputs!$B$63)/Inputs!$B$64) -> 0.13144965 | H60: =IF(5<=Inputs!$B$63,$D$20,$D$20+($D$52-$D$20)*(5-Inputs!$B$63)/Inputs!$B$64) -> 0.13144965 | I60: =IF(6<=Inputs!$B$63,$D$20,$D$20+($D$52-$D$20)*(6-Inputs!$B$63)/Inputs!$B$64) -> 0.12113611 | J60: =IF(7<=Inputs!$B$63,$D$20,$D$20+($D$52-$D$20)*(7-Inputs!$B$63)/Inputs!$B$64) -> 0.11082258 | K60: =IF(8<=Inputs!$B$63,$D$20,$D$20+($D$52-$D$20)*(8-Inputs!$B$63)/Inputs!$B$64) -> 0.10050904 | L60: =IF(9<=Inputs!$B$63,$D$20,$D$20+($D$52-$D$20)*(9-Inputs!$B$63)/Inputs!$B$64) -> 0.090195508 | M60: =IF(10<=Inputs!$B$63,$D$20,$D$20+($D$52-$D$20)*(10-Inputs!$B$63)/Inputs!$B$64) -> 0.079881973
B61: Tax rate (fading to statutory) | D61: =$D$11+($D$53-$D$11)*1/$D$55 -> 0.26669663 | E61: =$D$11+($D$53-$D$11)*2/$D$55 -> 0.26373034 | F61: =$D$11+($D$53-$D$11)*3/$D$55 -> 0.26076404 | G61: =$D$11+($D$53-$D$11)*4/$D$55 -> 0.25779775 | H61: =$D$11+($D$53-$D$11)*5/$D$55 -> 0.25483146 | I61: =$D$11+($D$53-$D$11)*6/$D$55 -> 0.25186517 | J61: =$D$11+($D$53-$D$11)*7/$D$55 -> 0.24889888 | K61: =$D$11+($D$53-$D$11)*8/$D$55 -> 0.24593258 | L61: =$D$11+($D$53-$D$11)*9/$D$55 -> 0.24296629 | M61: =$D$11+($D$53-$D$11)*10/$D$55 -> 0.24 | N61: Effective rate today, statutory by year 10. Tax shields erode.
B62: EBIT | D62: =$D$8*(1+D59) -> 547.57631 | E62: =D62*(1+E59) -> 566.15684 | F62: =E62*(1+F59) -> 585.36786 | G62: =F62*(1+G59) -> 605.23074 | H62: =G62*(1+H59) -> 625.76762 | I62: =H62*(1+I59) -> 646.00861 | J62: =I62*(1+J59) -> 665.87944 | K62: =J62*(1+K59) -> 685.30509 | L62: =K62*(1+L59) -> 704.21024 | M62: =L62*(1+M59) -> 722.5197
B63: NOPAT | D63: =D62*(1-D61) -> 401.53956 | E63: =E62*(1-E61) -> 416.84411 | F63: =F62*(1-F61) -> 432.72497 | G63: =G62*(1-G61) -> 449.20362 | H63: =H62*(1-H61) -> 466.30235 | I63: =I62*(1-I61) -> 483.30154 | J63: =J62*(1-J61) -> 500.1428 | K63: =K62*(1-K61) -> 516.76624 | ... M63: =M62*(1-M61) -> 549.11497
B64: Reinvestment rate | D64: =IF(D60<=0,0,MIN(1,MAX(0,D59/D60))) -> 0.25813927 | E64: =IF(E60<=0,0,MIN(1,MAX(0,E59/E60))) -> 0.25813927 | F64: =IF(F60<=0,0,MIN(1,MAX(0,F59/F60))) -> 0.25813927 | G64: =IF(G60<=0,0,MIN(1,MAX(0,G59/G60))) -> 0.25813927 | H64: =IF(H60<=0,0,MIN(1,MAX(0,H59/H60))) -> 0.25813927 | I64: =IF(I60<=0,0,MIN(1,MAX(0,I59/I60))) -> 0.26702072 | J64: =IF(J60<=0,0,MIN(1,MAX(0,J59/J60))) -> 0.27755526 | K64: =IF(K60<=0,0,MIN(1,MAX(0,K59/K60))) -> 0.29025176 | ... M64: =IF(M60<=0,0,MIN(1,MAX(0,M59/M60))) -> 0.32548019
B65: Free cash flow to the firm | D65: =D63*(1-D64) -> 297.88643 | E65: =E63*(1-E64) -> 309.24028 | F65: =F63*(1-F64) -> 321.02166 | G65: =G63*(1-G64) -> 333.24652 | H65: =H63*(1-H64) -> 345.9314 | I65: =I63*(1-I64) -> 354.25001 | J65: =J63*(1-J64) -> 361.32553 | K65: =K63*(1-K64) -> 366.77393 | ... M65: =M63*(1-M64) -> 370.38893
B66: Discount factor | D66: =1/(1+$D$47)^(1-$D$54) -> 0.96230303 | E66: =1/(1+$D$47)^(2-$D$54) -> 0.89111871 | F66: =1/(1+$D$47)^(3-$D$54) -> 0.8252001 | G66: =1/(1+$D$47)^(4-$D$54) -> 0.76415768 | H66: =1/(1+$D$47)^(5-$D$54) -> 0.70763074 | I66: =1/(1+$D$47)^(6-$D$54) -> 0.65528526 | J66: =1/(1+$D$47)^(7-$D$54) -> 0.60681192 | K66: =1/(1+$D$47)^(8-$D$54) -> 0.5619243 | L66: =1/(1+$D$47)^(9-$D$54) -> 0.52035715 | M66: =1/(1+$D$47)^(10-$D$54) -> 0.48186483
B67: Present value | D67: =D65*D66 -> 286.65701 | E67: =E65*E66 -> 275.5698 | F67: =F65*F66 -> 264.90711 | G67: =G65*G66 -> 254.65289 | H67: =H65*H66 -> 244.79169 | I67: =I65*I66 -> 232.13481 | J67: =J65*J66 -> 219.25664 | K67: =K65*K66 -> 206.09918 | ... M67: =M65*M66 -> 178.4774
B69: G. VALUATION
B70: PV of explicit-period cash flows | D70: =SUM(D67:M67) -> 2355.1088
B71: Terminal-year NOPAT (year 11) | D71: =M63*(1+D51) -> 563.39196
B72: Terminal reinvestment rate | D72: =IF(D52<=0,0,D51/D52) -> 0.32548019
B73: Terminal free cash flow | D73: =D71*(1-D72) -> 380.01904
B74: Terminal value at year 10 | D74: =D73/MAX(D47-D51,Inputs!B70) -> 7052.8048
B75: PV of terminal value | D75: =D74/(1+D47)^(D55-D54) -> 3398.4986 | N75: Mid-year offset applied here too — corrects the v1 inconsistency.
B76: Enterprise value | D76: =D70+D75 -> 5753.6074
B77: less: total debt | D77: =-D33 -> -1345
B78: less: preferred stock | D78: =-Inputs!F36 -> 0
B79: less: minority interest | D79: =-Inputs!F37 -> -58
B80: plus: cash & short-term investments | D80: =Inputs!F30+Inputs!F31 -> 360
B81: plus: equity-method investments (book) | D81: =Inputs!F39 -> 100
B82: Equity value | D82: =D76+D77+D78+D79+D80+D81 -> 4810.6074
B83: Value per share | D83: =IFERROR(D82/Inputs!B15,0) -> 11.453827
B84: Current share price | D84: =Inputs!B14 -> 24.5
B85: Upside / (downside) | D85: =IFERROR(D83/D84-1,0) -> -0.53249685
B86: VERDICT | D86: =IF(SUMPRODUCT(--(LEFT(D96:D122,4)="FAIL"))>0,"VOID - failed validation",IF(D85>0.25,"UNDERVALUED - investigate",IF(D85<-0.25,"OVERVALUED - screen out","FAIRLY VALUED - no action"))) -> OVERVALUED - screen out
B88: H. DIAGNOSTICS
B89: Terminal value as share of enterprise value | D89: =IFERROR(D75/D76,0) -> 0.59067266
B90: Normalised margin vs industry median (x) | D90: =IFERROR(D7/Inputs!B59,0) -> 1.1158988
B91: Normalised ROIC vs industry median (x) | D91: =IFERROR(D20/Inputs!B60,0) -> 1.3836805
B92: Equity-method investments as share of total assets | D92: =IFERROR(Inputs!F39/Inputs!F40,0) -> 0.019417476
B93: Implied enterprise value / EBIT | D93: =IFERROR(D76/D8,0) -> 10.863948
B95: I. VALIDATION CHECKS (severity is the first word of the result: FAIL voids the valuation; WARNING and NOTE do not)
B96: Normalised NOPAT is positive | D96: =IF(D12>0,"OK","FAIL - normalised NOPAT is negative; FCFF valuation not meaningful") -> OK
B97: Invested capital is positive | D97: =IF(D18>0,"OK","FAIL - average invested capital is zero or negative; ROIC undefined") -> OK
B98: WACC exceeds terminal growth | D98: =IF(D47-D51>=Inputs!B70,"OK","FAIL - WACC does not exceed terminal growth; terminal value meaningless") -> OK
B99: Stage lengths sum to the forecast horizon | D99: =IF(Inputs!B63+Inputs!B64=10,"OK","FAIL - stage 1 and stage 2 must sum to 10 years") -> OK
B100: Value per share is positive | D100: =IF(D83>0,"OK","FAIL - equity value is negative") -> OK
B101: Terminal value is not dominant | D101: =IF(D89<=0.85,"OK","WARNING - terminal value exceeds 85% of enterprise value") -> OK
B102: Interest coverage is adequate | D102: =IF(D38>=1.5,"OK","WARNING - interest coverage below 1.5x; distress risk") -> OK
B103: Cost of debt source | D103: =IF(D42<=D41,"OK","WARNING - actual interest cost exceeds the synthetic spread; possible credit deterioration") -> OK
B104: Reinvestment estimates agree | D104: =IF(D30<=0.5,"OK","WARNING - cash-flow and sales-to-capital reinvestment estimates diverge by more than 50%") -> OK
B105: Margin is plausible against the industry | D105: =IF(AND(D90>=0.4,D90<=2.5),"OK","WARNING - normalised margin is far from the industry median; check the data") -> OK
B106: ROIC is plausible against the industry | D106: =IF(AND(D91>=0.3,D91<=3),"OK","NOTE - normalised ROIC is far from the industry median") -> OK
B107: ROIC bound not binding | D107: =IF(AND(D19<Inputs!B66,D19>Inputs!B67),"OK","NOTE - normalised ROIC was capped or floored") -> OK
B108: Growth bound not binding | D108: =IF(D29*D20<Inputs!B65,"OK","NOTE - fundamental growth was capped") -> OK
B109: Effective tax rate used as reported | D109: =IF(AND(D10>=0.05,D10<=0.45),"OK","NOTE - median effective tax rate implausible; statutory rate substituted") -> OK
...

Sheet Sensitivity
B1: SENSITIVITY — VALUE PER SHARE
B2: The operating forecast is held fixed; only the discount rate and the terminal growth rate move. This isolates the effect of the cost of capital, which is the least observable input in the model.
B4: Terminal growth -> | C4: =Valuation!$D$51+-0.005 -> 0.021 | D4: =Valuation!$D$51+0 -> 0.026 | E4: =Valuation!$D$51+0.005 -> 0.031
B5: =Valuation!$D$47+-0.01 -> 0.069881973 | C5: =IFERROR((SUMPRODUCT(Valuation!$D$65:$M$65/(1+$B5)^(Valuation!$D$58:$M$58-Valuation!$D$54))+(Valuation!$M$63*(1+C$4)*(1-C$4/MAX($B5,C$4+Inputs!$B$70))/MAX($B5-C$4,Inputs!$B$70))/(1+$B5)^(Valuation!$D$55-Valuation!$D$54)+(Valuation!$D$82-Valuation!$D$76))/Inputs!$B$15,0) -> 13.663454 | D5: =IFERROR((SUMPRODUCT(Valuation!$D$65:$M$65/(1+$B5)^(Valuation!$D$58:$M$58-Valuation!$D$54))+(Valuation!$M$63*(1+D$4)*(1-D$4/MAX($B5,D$4+Inputs!$B$70))/MAX($B5-D$4,Inputs!$B$70))/(1+$B5)^(Valuation!$D$55-Valuation!$D$54)+(Valuation!$D$82-Valuation!$D$76))/Inputs!$B$15,0) -> 13.712695 | E5: =IFERROR((SUMPRODUCT(Valuation!$D$65:$M$65/(1+$B5)^(Valuation!$D$58:$M$58-Valuation!$D$54))+(Valuation!$M$63*(1+E$4)*(1-E$4/MAX($B5,E$4+Inputs!$B$70))/MAX($B5-E$4,Inputs!$B$70))/(1+$B5)^(Valuation!$D$55-Valuation!$D$54)+(Valuation!$D$82-Valuation!$D$76))/Inputs!$B$15,0) -> 13.761936
B6: =Valuation!$D$47+-0.005 -> 0.074881973 | C6: =IFERROR((SUMPRODUCT(Valuation!$D$65:$M$65/(1+$B6)^(Valuation!$D$58:$M$58-Valuation!$D$54))+(Valuation!$M$63*(1+C$4)*(1-C$4/MAX($B6,C$4+Inputs!$B$70))/MAX($B6-C$4,Inputs!$B$70))/(1+$B6)^(Valuation!$D$55-Valuation!$D$54)+(Valuation!$D$82-Valuation!$D$76))/Inputs!$B$15,0) -> 12.460261 | D6: =IFERROR((SUMPRODUCT(Valuation!$D$65:$M$65/(1+$B6)^(Valuation!$D$58:$M$58-Valuation!$D$54))+(Valuation!$M$63*(1+D$4)*(1-D$4/MAX($B6,D$4+Inputs!$B$70))/MAX($B6-D$4,Inputs!$B$70))/(1+$B6)^(Valuation!$D$55-Valuation!$D$54)+(Valuation!$D$82-Valuation!$D$76))/Inputs!$B$15,0) -> 12.504223 | E6: =IFERROR((SUMPRODUCT(Valuation!$D$65:$M$65/(1+$B6)^(Valuation!$D$58:$M$58-Valuation!$D$54))+(Valuation!$M$63*(1+E$4)*(1-E$4/MAX($B6,E$4+Inputs!$B$70))/MAX($B6-E$4,Inputs!$B$70))/(1+$B6)^(Valuation!$D$55-Valuation!$D$54)+(Valuation!$D$82-Valuation!$D$76))/Inputs!$B$15,0) -> 12.548185
B7: =Valuation!$D$47+0 -> 0.079881973 | C7: =IFERROR((SUMPRODUCT(Valuation!$D$65:$M$65/(1+$B7)^(Valuation!$D$58:$M$58-Valuation!$D$54))+(Valuation!$M$63*(1+C$4)*(1-C$4/MAX($B7,C$4+Inputs!$B$70))/MAX($B7-C$4,Inputs!$B$70))/(1+$B7)^(Valuation!$D$55-Valuation!$D$54)+(Valuation!$D$82-Valuation!$D$76))/Inputs!$B$15,0) -> 11.414394 | D7: =IFERROR((SUMPRODUCT(Valuation!$D$65:$M$65/(1+$B7)^(Valuation!$D$58:$M$58-Valuation!$D$54))+(Valuation!$M$63*(1+D$4)*(1-D$4/MAX($B7,D$4+Inputs!$B$70))/MAX($B7-D$4,Inputs!$B$70))/(1+$B7)^(Valuation!$D$55-Valuation!$D$54)+(Valuation!$D$82-Valuation!$D$76))/Inputs!$B$15,0) -> 11.453827 | E7: =IFERROR((SUMPRODUCT(Valuation!$D$65:$M$65/(1+$B7)^(Valuation!$D$58:$M$58-Valuation!$D$54))+(Valuation!$M$63*(1+E$4)*(1-E$4/MAX($B7,E$4+Inputs!$B$70))/MAX($B7-E$4,Inputs!$B$70))/(1+$B7)^(Valuation!$D$55-Valuation!$D$54)+(Valuation!$D$82-Valuation!$D$76))/Inputs!$B$15,0) -> 11.49326
B8: =Valuation!$D$47+0.005 -> 0.084881973 | C8: =IFERROR((SUMPRODUCT(Valuation!$D$65:$M$65/(1+$B8)^(Valuation!$D$58:$M$58-Valuation!$D$54))+(Valuation!$M$63*(1+C$4)*(1-C$4/MAX($B8,C$4+Inputs!$B$70))/MAX($B8-C$4,Inputs!$B$70))/(1+$B8)^(Valuation!$D$55-Valuation!$D$54)+(Valuation!$D$82-Valuation!$D$76))/Inputs!$B$15,0) -> 10.497733 | D8: =IFERROR((SUMPRODUCT(Valuation!$D$65:$M$65/(1+$B8)^(Valuation!$D$58:$M$58-Valuation!$D$54))+(Valuation!$M$63*(1+D$4)*(1-D$4/MAX($B8,D$4+Inputs!$B$70))/MAX($B8-D$4,Inputs!$B$70))/(1+$B8)^(Valuation!$D$55-Valuation!$D$54)+(Valuation!$D$82-Valuation!$D$76))/Inputs!$B$15,0) -> 10.53325 | E8: =IFERROR((SUMPRODUCT(Valuation!$D$65:$M$65/(1+$B8)^(Valuation!$D$58:$M$58-Valuation!$D$54))+(Valuation!$M$63*(1+E$4)*(1-E$4/MAX($B8,E$4+Inputs!$B$70))/MAX($B8-E$4,Inputs!$B$70))/(1+$B8)^(Valuation!$D$55-Valuation!$D$54)+(Valuation!$D$82-Valuation!$D$76))/Inputs!$B$15,0) -> 10.568766
B9: =Valuation!$D$47+0.01 -> 0.089881973 | C9: =IFERROR((SUMPRODUCT(Valuation!$D$65:$M$65/(1+$B9)^(Valuation!$D$58:$M$58-Valuation!$D$54))+(Valuation!$M$63*(1+C$4)*(1-C$4/MAX($B9,C$4+Inputs!$B$70))/MAX($B9-C$4,Inputs!$B$70))/(1+$B9)^(Valuation!$D$55-Valuation!$D$54)+(Valuation!$D$82-Valuation!$D$76))/Inputs!$B$15,0) -> 9.6884294 | D9: =IFERROR((SUMPRODUCT(Valuation!$D$65:$M$65/(1+$B9)^(Valuation!$D$58:$M$58-Valuation!$D$54))+(Valuation!$M$63*(1+D$4)*(1-D$4/MAX($B9,D$4+Inputs!$B$70))/MAX($B9-D$4,Inputs!$B$70))/(1+$B9)^(Valuation!$D$55-Valuation!$D$54)+(Valuation!$D$82-Valuation!$D$76))/Inputs!$B$15,0) -> 9.7205369 | E9: =IFERROR((SUMPRODUCT(Valuation!$D$65:$M$65/(1+$B9)^(Valuation!$D$58:$M$58-Valuation!$D$54))+(Valuation!$M$63*(1+E$4)*(1-E$4/MAX($B9,E$4+Inputs!$B$70))/MAX($B9-E$4,Inputs!$B$70))/(1+$B9)^(Valuation!$D$55-Valuation!$D$54)+(Valuation!$D$82-Valuation!$D$76))/Inputs!$B$15,0) -> 9.7526444
B12: Current share price | C12: =Inputs!B14 -> 24.5
B13: Base-case value per share | C13: =Valuation!D83 -> 11.453827

Sheet Instructions
B1: READ ME — MODEL v2.2
B3: WHAT CHANGED FROM v1
B4: 1. Beta is now bottom-up. An industry unlevered beta is relevered at the company's own debt-to-equity ratio and country tax rate. The five-year regression against a market index is gone, along with its standard error, the Blume adjustment, the index price series, and the 36-month minimum history requirement.
B5: 2. Normalisation uses the five-year MEDIAN, not the three-year mean. A single distorted year no longer moves the result, and no one has to decide which year was distorted.
B6: 3. The tax rate fades. Stage 1 starts at the company's own median effective rate and converges linearly to the country statutory rate by year 10, because tax shields erode. v1 switched between the two discontinuously.
B7: 4. Mid-year discounting is now applied to the terminal value as well as the explicit years. In v1 it was applied only to the explicit period, which understated value by roughly 3%.
B8: 5. Reinvestment is estimated twice — from cash flows and from the industry sales-to-capital ratio — and the LOWER estimate is used. Conservative by rule.
B9: 6. The cost of debt is the HIGHER of the synthetic spread and the company's actual effective interest rate, capped at 25%.
B10: 7. Five new validation checks: reinvestment divergence, cost-of-debt source, margin and ROIC against industry medians, and a holding-company test on equity-method investments.
B12: THE INPUT RULE
B13: Every input is either (a) read directly from the financial statements, (b) a market-wide parameter, (c) a country parameter set by domicile, or (d) an industry parameter. There are no company-specific judgement values anywhere. If a future change would require one, it does not belong in this model.
B15: WHAT THIS MODEL IS FOR
... B43: The cut-off is fixed in EUR and reviewed annually. A cut-off that floated with EURUSD would reclassify companies, and change their valuations, for no economic reason. D121 warns when a company sits within 20% of it.
